CHANGELOG
COPYRIGHT
INSTALL
LICENSE
MANIFEST.in
README
sale.xml
setup.py
tryton.cfg
./__init__.py
./sale.py
./tests/__init__.py
./tests/test_sale_salesman.py
doc/index.rst
locale/ca_ES.po
locale/es_ES.po
trytonzz_sale_salesman.egg-info/PKG-INFO
trytonzz_sale_salesman.egg-info/SOURCES.txt
trytonzz_sale_salesman.egg-info/dependency_links.txt
trytonzz_sale_salesman.egg-info/entry_points.txt
trytonzz_sale_salesman.egg-info/not-zip-safe
trytonzz_sale_salesman.egg-info/requires.txt
trytonzz_sale_salesman.egg-info/top_level.txt