Metadata-Version: 1.0
Name: trytonzz-sale-salesman
Version: 3.4.0
Summary: Tryton module. Add salesman in sale
Home-page: http://www.zikzakmedia.com
Author: Zikzakmedia SL
Author-email: zikzak@zikzakmedia.com
License: GPL-3
Download-URL: https://bitbucket.org/zikzakmedia/trytond-sale_salesman
Platform: UNKNOWN
Classifier: Development Status :: 5 - Production/Stable
Classifier: Environment :: Plugins
Classifier: Framework :: Tryton
Classifier: Intended Audience :: Developers
Classifier: Intended Audience :: Financial and Insurance Industry
Classifier: Intended Audience :: Legal Industry
Classifier: Intended Audience :: Manufacturing
Classifier: License :: OSI Approved :: GNU General Public License (GPL)
Classifier: Natural Language :: Catalan
Classifier: Natural Language :: Spanish
Classifier: Operating System :: OS Independent
Classifier: Programming Language :: Python :: 2.6
Classifier: Programming Language :: Python :: 2.7
Classifier: Topic :: Office/Business
